[
  {
    "id": 1,
    "firstName": "Mariann",
    "lastName": "Maffioletti",
    "phone": "705-249-3278",
    "address": "6 Aberg Park",
    "heatType": "boiler",
    "nextStep": "return call",
    "status": "coach",
    "city": "Kalilangan",
    "zipCode": "8718"
  },
  {
    "id": 2,
    "firstName": "Ibby",
    "lastName": "Giannotti",
    "phone": "797-488-0690",
    "address": "9750 Novick Court",
    "heatType": "boiler",
    "nextStep": "review",
    "status": "review",
    "city": "São José dos Campos",
    "zipCode": "12200-000"
  },
  {
    "id": 3,
    "firstName": "Clem",
    "lastName": "Gherardesci",
    "phone": "221-267-1949",
    "address": "0 Almo Alley",
    "heatType": "boiler",
    "nextStep": "no response",
    "status": "completed",
    "city": "Rače",
    "zipCode": "2327"
  },
  {
    "id": 4,
    "firstName": "Tarrance",
    "lastName": "Basil",
    "phone": "323-691-1816",
    "address": "73405 Melody Trail",
    "heatType": "boiler",
    "nextStep": "call",
    "status": "review",
    "city": "Grande Prairie",
    "zipCode": "R3J"
  },
  {
    "id": 5,
    "firstName": "Waring",
    "lastName": "Snassell",
    "phone": "902-292-8904",
    "address": "1 Esch Street",
    "heatType": "boiler",
    "nextStep": "call",
    "status": "review",
    "city": "La Sarre",
    "zipCode": "J9Z"
  },
  {
    "id": 6,
    "firstName": "Cicely",
    "lastName": "Brightman",
    "phone": "538-372-2331",
    "address": "73768 Pepper Wood Court",
    "heatType": "boiler",
    "nextStep": "call",
    "status": "review",
    "city": "Donghe"
  },
  {
    "id": 7,
    "firstName": "Oona",
    "lastName": "McCrossan",
    "phone": "707-828-4003",
    "address": "48 Lyons Parkway",
    "heatType": "boiler",
    "nextStep": "call",
    "status": "review",
    "city": "Napanee Downtown",
    "zipCode": "M5E"
  },
  {
    "id": 8,
    "firstName": "Othilia",
    "lastName": "Rickman",
    "phone": "180-495-8589",
    "address": "621 Buena Vista Place",
    "heatType": "boiler",
    "nextStep": "call",
    "status": "review",
    "city": "Sukabumi"
  },
  {
    "id": 9,
    "firstName": "Enrica",
    "lastName": "Baumler",
    "phone": "934-959-4320",
    "address": "1601 Trailsway Point",
    "heatType": "boiler",
    "nextStep": "call",
    "status": "review",
    "city": "Portela",
    "zipCode": "3140-480"
  },
  {
    "id": 10,
    "firstName": "Bobbette",
    "lastName": "Iliffe",
    "phone": "241-360-6848",
    "address": "40 Merry Avenue",
    "heatType": "boiler",
    "nextStep": "call",
    "status": "review",
    "city": "Herrera",
    "zipCode": "4326"
  },
  {
    "id": 11,
    "firstName": "Durward",
    "lastName": "Shorto",
    "phone": "169-628-2698",
    "address": "90038 Grayhawk Street",
    "heatType": "boiler",
    "nextStep": "call",
    "status": "review",
    "city": "Shiqiao"
  },
  {
    "id": 12,
    "firstName": "Coop",
    "lastName": "Edler",
    "phone": "559-244-7888",
    "address": "14 Messerschmidt Drive",
    "heatType": "boiler",
    "nextStep": "call",
    "status": "review",
    "city": "Balut",
    "zipCode": "8420"
  },
  {
    "id": 13,
    "firstName": "Rolph",
    "lastName": "Barrett",
    "phone": "908-252-5824",
    "address": "414 Sunfield Crossing",
    "heatType": "boiler",
    "nextStep": "call",
    "status": "review",
    "city": "Porsgrunn",
    "zipCode": "3912"
  },
  {
    "id": 14,
    "firstName": "Inna",
    "lastName": "Stokell",
    "phone": "546-934-6197",
    "address": "34314 Moose Point",
    "heatType": "boiler",
    "nextStep": "call",
    "status": "review",
    "city": "Kosów Lacki",
    "zipCode": "08-330"
  },
  {
    "id": 15,
    "firstName": "Oliviero",
    "lastName": "Gresty",
    "phone": "997-973-9261",
    "address": "26510 Atwood Way",
    "heatType": "boiler",
    "nextStep": "call",
    "status": "review",
    "city": "Pskov",
    "zipCode": "180559"
  },
  {
    "id": 16,
    "firstName": "Elyn",
    "lastName": "Richen",
    "phone": "318-277-3201",
    "address": "084 Sundown Street",
    "heatType": "boiler",
    "nextStep": "call",
    "status": "review",
    "city": "Handan"
  },
  {
    "id": 17,
    "firstName": "Giffard",
    "lastName": "Cluse",
    "phone": "236-346-4053",
    "address": "06818 Mandrake Drive",
    "heatType": "boiler",
    "nextStep": "call",
    "status": "review",
    "city": "Ylöjärvi",
    "zipCode": "33480"
  },
  {
    "id": 18,
    "firstName": "Raffaello",
    "lastName": "Rosedale",
    "phone": "115-338-0035",
    "address": "1913 Truax Place",
    "heatType": "boiler",
    "nextStep": "call",
    "status": "review",
    "city": "Granadero Baigorria",
    "zipCode": "2152"
  },
  {
    "id": 19,
    "firstName": "Hadley",
    "lastName": "Sweetman",
    "phone": "698-844-0990",
    "address": "458 Nova Pass",
    "heatType": "boiler",
    "nextStep": "call",
    "status": "review",
    "city": "Westport",
    "zipCode": "7866"
  },
  {
    "id": 20,
    "firstName": "Serge",
    "lastName": "Ryde",
    "phone": "132-873-5154",
    "address": "6015 American Place",
    "heatType": "boiler",
    "nextStep": "call",
    "status": "review",
    "city": "Tanghua"
  }
]
